{
	"dialogue": [
		{
			"speed": 0.05,
			"portrait": "bf",
			"boxState": "normal",
			"expression": "talk",
			"text": "boop beep"
		},
		{
			"speed": 0.05,
			"portrait": "gf",
			"boxState": "normal",
			"expression": "talk",
			"text": "Yeah Boyfriend, you did do cool out there ^^"
		},
		{
			"speed": 0.05,
			"portrait": "gf",
			"boxState": "normal",
			"expression": "confused",
			"text": "Say...where are we?"
		},
		{
			"speed": 0.05,
			"portrait": "bf",
			"boxState": "normal",
			"expression": "shocked",
			"text": "booooop.....bap bo skat?"
		},
		{
			"speed": 0.05,
			"portrait": "skid",
			"boxState": "normal",
			"expression": "talk",
			"text": "WHY HELLO THERE FELLOW HUMANS!!!"
		},
		{
			"speed": 0.05,
			"portrait": "pump",
			"boxState": "normal",
			"expression": "talk",
			"text": "HOWDY! :>"
		},
		{
			"speed": 0.05,
			"portrait": "gf",
			"boxState": "normal",
			"expression": "shocked",
			"text": "EEEEK!!! MONSTERS!!!"
		},
		{
			"speed": 0.05,
			"portrait": "bf",
			"boxState": "normal",
			"expression": "shocked",
			"text": "BO BAP SKEE BOP!!!"
		},
		{
			"speed": 0.05,
			"portrait": "pump",
			"boxState": "normal",
			"expression": "talk",
			"text": "Oh don't Be afraid of us, we  are The Spooky Kids!!^^"
		},
		{
			"speed": 0.05,
			"portrait": "gf",
			"boxState": "normal",
			"expression": "confused",
			"text": "Spooky...Kids?"
		},
		{
			"speed": 0.05,
			"portrait": "bf",
			"boxState": "normal",
			"expression": "talk",
			"text": "bo...beep?"
		},
		{
			"speed": 0.05,
			"portrait": "skid",
			"boxState": "normal",
			"expression": "talk",
			"text": "Yes! ^^"
		},
		{
			"speed": 0.05,
			"portrait": "skid",
			"boxState": "normal",
			"expression": "talk",
			"text": "I'm Skid!"
		},
		{
			"speed": 0.05,
			"portrait": "pump",
			"boxState": "normal",
			"expression": "talk",
			"text": "and I'm Pump! ^^"
		},
		{
			"speed": 0.05,
			"portrait": "bf",
			"boxState": "normal",
			"expression": "excited",
			"text": "beep bap skee bap bo"
		},
		{
			"speed": 0.05,
			"portrait": "skid",
			"boxState": "normal",
			"expression": "talk",
			"text": "What's that? You wanna sing with us?"
		},
		{
			"speed": 0.05,
			"portrait": "bf",
			"boxState": "normal",
			"expression": "excited",
			"text": "beep bap skee!"
		},
		{
			"speed": 0.05,
			"portrait": "pump",
			"boxState": "normal",
			"expression": "talk",
			"text": "OH BOY!!! "
		},
		{
			"speed": 0.05,
			"portrait": "gf",
			"boxState": "normal",
			"expression": "confused",
			"text": "Y-yes. I'm sure singing wouldn't hurt. *was scared of the thunder*"
		}
	]
}